gitbackup/__init__.py
gitbackup/cli.py
github_back_up-1.0.dist-info/METADATA
github_back_up-1.0.dist-info/WHEEL
github_back_up-1.0.dist-info/entry_points.txt
github_back_up-1.0.dist-info/top_level.txt
github_back_up-1.0.dist-info/RECORD
