Metadata-Version: 2.1
Name: github-back-up
Version: 1.0
Summary: Github Backup
Home-page: UNKNOWN
Author: Philippe Remy
License: MIT
Platform: UNKNOWN
Requires-Dist: gitpython
Requires-Dist: PyGithub
Requires-Dist: tqdm
Requires-Dist: click
